sm4file/__init__.py
sm4file/cursor.py
sm4file/py.typed
sm4file/sm4_file.py
sm4file/sm4_object_types.py
sm4file-0.1.0.dist-info/LICENSE
sm4file-0.1.0.dist-info/METADATA
sm4file-0.1.0.dist-info/WHEEL
sm4file-0.1.0.dist-info/RECORD
