Metadata-Version: 2.1
Name: sm4file
Version: 0.1.0
Summary: Python package to read .sm4 files
License: BSD-3-Clause
Author: matkrin
Author-email: matkrin@protonmail.com
Requires-Python: >=3.9
Classifier: License :: OSI Approved :: BSD License
Classifier: Programming Language :: Python :: 3
Classifier: Programming Language :: Python :: 3.9
Classifier: Programming Language :: Python :: 3.10
Classifier: Programming Language :: Python :: 3.11
Classifier: Programming Language :: Python :: 3.12
Requires-Dist: numpy (>=1.26.0)
